[{"fields": {"nombre": "ANESTESIOLOGIA"}, "model": "main.especialidad", "pk": "00001"}, {"fields": {"nombre": "ANGIOLOGIA"}, "model": "main.especialidad", "pk": "00002"}, {"fields": {"nombre": "ADMINISTRACION DE HOSPITALES"}, "model": "main.especialidad", "pk": "00003"}, {"fields": {"nombre": "ANATOMIA PATOLOGICA"}, "model": "main.especialidad", "pk": "00004"}, {"fields": {"nombre": "ANATOMIA HUMANA"}, "model": "main.especialidad", "pk": "00005"}, {"fields": {"nombre": "BIOQUIMICA"}, "model": "main.especialidad", "pk": "00006"}, {"fields": {"nombre": "CIRUGIA TORACICA Y CARDIOVASCULAR"}, "model": "main.especialidad", "pk": "00007"}, {"fields": {"nombre": "CARDIOLOGIA"}, "model": "main.especialidad", "pk": "00008"}, {"fields": {"nombre": "CIRUGIA GENERAL"}, "model": "main.especialidad", "pk": "00009"}, {"fields": {"nombre": "CIRUGIA DE CABEZA Y CUELLO Y MAXILO FACIAL"}, "model": "main.especialidad", "pk": "00010"}, {"fields": {"nombre": "CIRUGIA PEDIATRICA"}, "model": "main.especialidad", "pk": "00011"}, {"fields": {"nombre": "CIRUGIA PLASTICA Y REPARADORA"}, "model": "main.especialidad", "pk": "00012"}, {"fields": {"nombre": "DERMATOLOGIA"}, "model": "main.especialidad", "pk": "00013"}, {"fields": {"nombre": "ENDOCRINOLOGIA"}, "model": "main.especialidad", "pk": "00014"}, {"fields": {"nombre": "ENFERMEDADES INFECCIOSAS Y TROPICALES"}, "model": "main.especialidad", "pk": "00015"}, {"fields": {"nombre": "EMBRIOLOGIA"}, "model": "main.especialidad", "pk": "00016"}, {"fields": {"nombre": "EPIDEMIOLOGIA"}, "model": "main.especialidad", "pk": "00017"}, {"fields": {"nombre": "FISIOLOGIA"}, "model": "main.especialidad", "pk": "00018"}, {"fields": {"nombre": "FARMACOLOGIA"}, "model": "main.especialidad", "pk": "00019"}, {"fields": {"nombre": "GASTROENTEROLOGIA"}, "model": "main.especialidad", "pk": "00020"}, {"fields": {"nombre": "GINECOLOGIA Y OBSTETRICIA"}, "model": "main.especialidad", "pk": "00021"}, {"fields": {"nombre": "GERIATRIA"}, "model": "main.especialidad", "pk": "00022"}, {"fields": {"nombre": "GENETICA"}, "model": "main.especialidad", "pk": "00023"}, {"fields": {"nombre": "HEMATOLOGIA"}, "model": "main.especialidad", "pk": "00024"}, {"fields": {"nombre": "HISTOLOGIA"}, "model": "main.especialidad", "pk": "00025"}, {"fields": {"nombre": "INMUNOLOGIA Y ALERGIA"}, "model": "main.especialidad", "pk": "00026"}, {"fields": {"nombre": "MEDICINA NUCLEAR"}, "model": "main.especialidad", "pk": "00027"}, {"fields": {"nombre": "MEDICINA DEL TRABAJO"}, "model": "main.especialidad", "pk": "00028"}, {"fields": {"nombre": "MEDICINA INTERNA"}, "model": "main.especialidad", "pk": "00029"}, {"fields": {"nombre": "MEDICINA LEGAL"}, "model": "main.especialidad", "pk": "00030"}, {"fields": {"nombre": "MEDICINA FISICA Y REHABILITACION"}, "model": "main.especialidad", "pk": "00031"}, {"fields": {"nombre": "MEDICINA DEL DEPORTE"}, "model": "main.especialidad", "pk": "00032"}, {"fields": {"nombre": "NEFROLOGIA"}, "model": "main.especialidad", "pk": "00033"}, {"fields": {"nombre": "NEUMOLOGIA"}, "model": "main.especialidad", "pk": "00034"}, {"fields": {"nombre": "NEUROCIRUGIA"}, "model": "main.especialidad", "pk": "00035"}, {"fields": {"nombre": "NEUROLOGIA"}, "model": "main.especialidad", "pk": "00036"}, {"fields": {"nombre": "NUTRICION"}, "model": "main.especialidad", "pk": "00037"}, {"fields": {"nombre": "OFTALMOLOGIA"}, "model": "main.especialidad", "pk": "00038"}, {"fields": {"nombre": "ONCOLOGIA MEDICA"}, "model": "main.especialidad", "pk": "00039"}, {"fields": {"nombre": "ONCOLOGIA QUIRURGICA"}, "model": "main.especialidad", "pk": "00040"}, {"fields": {"nombre": "ORTOPEDIA Y TRAUMATOLOGIA"}, "model": "main.especialidad", "pk": "00041"}, {"fields": {"nombre": "OTORRINOLARINGOLOGIA"}, "model": "main.especialidad", "pk": "00042"}, {"fields": {"nombre": "PATOLOGIA CLINICA"}, "model": "main.especialidad", "pk": "00043"}, {"fields": {"nombre": "PEDIATRIA"}, "model": "main.especialidad", "pk": "00044"}, {"fields": {"nombre": "PSIQUIATRIA"}, "model": "main.especialidad", "pk": "00045"}, {"fields": {"nombre": "RADIOLOGIA"}, "model": "main.especialidad", "pk": "00046"}, {"fields": {"nombre": "RADIOTERAPIA"}, "model": "main.especialidad", "pk": "00047"}, {"fields": {"nombre": "REUMATOLOGIA"}, "model": "main.especialidad", "pk": "00048"}, {"fields": {"nombre": "SALUD PUBLICA"}, "model": "main.especialidad", "pk": "00049"}, {"fields": {"nombre": "UROLOGIA"}, "model": "main.especialidad", "pk": "00050"}, {"fields": {"nombre": "VENEREOLOGIA"}, "model": "main.especialidad", "pk": "00051"}, {"fields": {"nombre": "PROCTOLOGIA"}, "model": "main.especialidad", "pk": "00052"}, {"fields": {"nombre": "MEDICINA INTENSIVA"}, "model": "main.especialidad", "pk": "00053"}, {"fields": {"nombre": "MEDICINA OCUPACIONAL Y MEDIO AMBIENTE"}, "model": "main.especialidad", "pk": "00054"}, {"fields": {"nombre": "NEONATOLOGIA"}, "model": "main.especialidad", "pk": "00055"}, {"fields": {"nombre": "MEDICINA GENERAL INTEGRAL"}, "model": "main.especialidad", "pk": "00056"}, {"fields": {"nombre": "CIRUGIA GENERAL Y ONCOLOGICA"}, "model": "main.especialidad", "pk": "00057"}, {"fields": {"nombre": "MEDICINA GENERAL Y ONCOLOGICA"}, "model": "main.especialidad", "pk": "00058"}, {"fields": {"nombre": "INMUNOLOGIA Y REUMATOLOGIA"}, "model": "main.especialidad", "pk": "00059"}, {"fields": {"nombre": "NEUMOLOGIA PEDIATRICA"}, "model": "main.especialidad", "pk": "00060"}, {"fields": {"nombre": "MEDICINA DE EMERGENCIAS Y DESASTRES"}, "model": "main.especialidad", "pk": "00061"}, {"fields": {"nombre": "ADMINISTRACION DE SALUD"}, "model": "main.especialidad", "pk": "00062"}, {"fields": {"nombre": "MEDICINA FAMILIAR"}, "model": "main.especialidad", "pk": "00063"}, {"fields": {"nombre": "RADIODIAGNOSTICO"}, "model": "main.especialidad", "pk": "00064"}, {"fields": {"nombre": "LABORATORIO CLINICO"}, "model": "main.especialidad", "pk": "00065"}, {"fields": {"nombre": "NEFROLOGIA PEDIATRICA"}, "model": "main.especialidad", "pk": "00066"}, {"fields": {"nombre": "UROLOGIA GENERAL Y ONCOLOGICA"}, "model": "main.especialidad", "pk": "00067"}, {"fields": {"nombre": "PATOLOGIA Y LABORATORIO CLINICO"}, "model": "main.especialidad", "pk": "00068"}, {"fields": {"nombre": "PARASITOLOGIA"}, "model": "main.especialidad", "pk": "00069"}, {"fields": {"nombre": "CIRUGIA DE MANO"}, "model": "main.especialidad", "pk": "00070"}, {"fields": {"nombre": "CIRUGIA NEUMOLOGICA"}, "model": "main.especialidad", "pk": "00071"}, {"fields": {"nombre": "NEUROLOGIA PEDIATRICA"}, "model": "main.especialidad", "pk": "00072"}, {"fields": {"nombre": "HISTOPATOLOGIA"}, "model": "main.especialidad", "pk": "00073"}, {"fields": {"nombre": "ONCOLOGIA PEDIATRICA"}, "model": "main.especialidad", "pk": "00074"}, {"fields": {"nombre": "MEDICINA INTEGRAL Y GESTION EN SALUD"}, "model": "main.especialidad", "pk": "00075"}, {"fields": {"nombre": "GINECOLOGIA DE LA NI\u00d1A Y ADOLESCENTE"}, "model": "main.especialidad", "pk": "00076"}, {"fields": {"nombre": "ANATOMIA PATOLOGICA - PATOLOGIA CLINICA"}, "model": "main.especialidad", "pk": "00077"}, {"fields": {"nombre": "ANESTESIOLOGIA Y TERAPIA INTENSIVA CARDIOVASCULAR"}, "model": "main.especialidad", "pk": "00078"}, {"fields": {"nombre": "LABORATORIO CLINICO Y ANATOMIA PATOLOGICA"}, "model": "main.especialidad", "pk": "00079"}, {"fields": {"nombre": "MEDICINA INTENSIVA PEDIATRICA"}, "model": "main.especialidad", "pk": "00080"}, {"fields": {"nombre": "ENDOCRINOLOGIA PEDIATRICA Y GENETICA"}, "model": "main.especialidad", "pk": "00081"}, {"fields": {"nombre": "PSIQUIATRIA INFANTIL"}, "model": "main.especialidad", "pk": "00082"}, {"fields": {"nombre": "PATOLOGIA ONCOLOGICA"}, "model": "main.especialidad", "pk": "00083"}, {"fields": {"nombre": "INFECTOLOGIA PEDIATRICA"}, "model": "main.especialidad", "pk": "00084"}, {"fields": {"nombre": "GINECOLOGIA ONCOLOGICA"}, "model": "main.especialidad", "pk": "00085"}, {"fields": {"nombre": "GASTROENTEROLOGIA PEDIATRICA"}, "model": "main.especialidad", "pk": "00086"}, {"fields": {"nombre": "CIRUGIA CARDIOVASCULAR PEDIATRICA"}, "model": "main.especialidad", "pk": "00087"}, {"fields": {"nombre": "OFTALMOLOGIA ONCOLOGICA"}, "model": "main.especialidad", "pk": "00088"}, {"fields": {"nombre": "ADOLESCENTOLOGIA"}, "model": "main.especialidad", "pk": "00089"}, {"fields": {"nombre": "PATOLOGIA"}, "model": "main.especialidad", "pk": "00090"}, {"fields": {"nombre": "ENDOCRINOLOGIA PEDIATRICA"}, "model": "main.especialidad", "pk": "00091"}, {"fields": {"nombre": "CIRUGIA ONCOLOGICA DE CABEZA Y CUELLO"}, "model": "main.especialidad", "pk": "00092"}, {"fields": {"nombre": "CIRUGIA ONCOLOGICA DE MAMAS, TEJIDOS BLANDOS Y PIEL"}, "model": "main.especialidad", "pk": "00094"}, {"fields": {"nombre": "MEDICINA HIPERBARICA Y SUBACUATICA"}, "model": "main.especialidad", "pk": "00095"}, {"fields": {"nombre": "CIRUGIA VASCULAR Y ANGIOLOGIA"}, "model": "main.especialidad", "pk": "00097"}, {"fields": {"nombre": "CIRUGIA GASTROENTEROLOGICA"}, "model": "main.especialidad", "pk": "00098"}, {"fields": {"nombre": "CIRUGIA ORTOPEDICA Y TRAUMATOLOGIA"}, "model": "main.especialidad", "pk": "00101"}, {"fields": {"nombre": "CIRUGIA ONCOLOGICA"}, "model": "main.especialidad", "pk": "00104"}, {"fields": {"nombre": "INMUNOLOGIA CLINICA Y ALERGOLOGIA"}, "model": "main.especialidad", "pk": "00105"}, {"fields": {"nombre": "OFTALMOLOGIA PEDIATRICA Y ESTRABISMO"}, "model": "main.especialidad", "pk": "00106"}, {"fields": {"nombre": "DERMATOLOGIA Y VENEREOLOGIA"}, "model": "main.especialidad", "pk": "00107"}, {"fields": {"nombre": "CARDIOLOGIA INFANTIL"}, "model": "main.especialidad", "pk": "00108"}, {"fields": {"nombre": "CIRUGIA DEL APARATO DIGESTIVO"}, "model": "main.especialidad", "pk": "00109"}, {"fields": {"nombre": "UROLOGIA PEDIATRICA"}, "model": "main.especialidad", "pk": "00110"}, {"fields": {"nombre": "ANESTESIOLOGIA OBSTETRICA"}, "model": "main.especialidad", "pk": "00111"}, {"fields": {"nombre": "CIRUGIA CARDIOVASCULAR"}, "model": "main.especialidad", "pk": "00112"}, {"fields": {"nombre": "ANALISIS CLINICOS"}, "model": "main.especialidad", "pk": "00113"}, {"fields": {"nombre": "EPIDEMIOLOGIA DE CAMPO"}, "model": "main.especialidad", "pk": "00114"}, {"fields": {"nombre": "PEDIATRIA DE EMERGENCIAS Y DESASTRES"}, "model": "main.especialidad", "pk": "00115"}, {"fields": {"nombre": "RADIOLOGIA INTERVENCIONISTA"}, "model": "main.especialidad", "pk": "00116"}, {"fields": {"nombre": "ARTROSCOPIA Y CIRUGIA DE RODILLA"}, "model": "main.especialidad", "pk": "00117"}, {"fields": {"nombre": "TERAPIA INTENSIVA"}, "model": "main.especialidad", "pk": "00118"}, {"fields": {"nombre": "CIRUGIA ONCOLOGICA ABDOMINAL"}, "model": "main.especialidad", "pk": "00119"}, {"fields": {"nombre": "CIRUGIA CRANEOMAXILOFACIAL"}, "model": "main.especialidad", "pk": "00120"}, {"fields": {"nombre": "MEDICINA DE REHABILITACION"}, "model": "main.especialidad", "pk": "00121"}, {"fields": {"nombre": "MEDICINA INTERNA PEDIATRICA"}, "model": "main.especialidad", "pk": "00122"}, {"fields": {"nombre": "MEDICINA INTERNA - GASTROENTEROLOGIA"}, "model": "main.especialidad", "pk": "00123"}, {"fields": {"nombre": "HEMATOLOGIA Y HEMOTERAPIA"}, "model": "main.especialidad", "pk": "00124"}, {"fields": {"nombre": "CIRUGIA, TRANSPLANTOLOGIA Y ANDROLOGIA"}, "model": "main.especialidad", "pk": "00125"}, {"fields": {"nombre": "NEUROFISIOLOGIA CLINICA"}, "model": "main.especialidad", "pk": "00126"}, {"fields": {"nombre": "TOXICOLOGIA"}, "model": "main.especialidad", "pk": "00127"}, {"fields": {"nombre": "RADIOLOGIA E IMAGEN"}, "model": "main.especialidad", "pk": "00128"}, {"fields": {"nombre": "MEDICINA AEROESPACIAL"}, "model": "main.especialidad", "pk": "00129"}, {"fields": {"nombre": "HEMATOLOGIA PEDIATRICA"}, "model": "main.especialidad", "pk": "00130"}, {"fields": {"nombre": "HEMATOLOGIA Y HEMOTERAPIA"}, "model": "main.especialidad", "pk": "00131"}, {"fields": {"nombre": "ANESTESIA, ANALGESIA Y REANIMACION"}, "model": "main.especialidad", "pk": "00132"}, {"fields": {"nombre": "MEDICINA INTERNA Y PEDIATRIA"}, "model": "main.especialidad", "pk": "00133"}, {"fields": {"nombre": "ENDOCRINOLOGIA Y NUTRICION"}, "model": "main.especialidad", "pk": "00134"}, {"fields": {"nombre": "APARATO DIGESTIVO"}, "model": "main.especialidad", "pk": "00135"}, {"fields": {"nombre": "DIAGNOSTICO POR IMAGENES"}, "model": "main.especialidad", "pk": "10108"}, {"fields": {"nombre": "GESTION EN SALUD"}, "model": "main.especialidad", "pk": "10111"}, {"fields": {"nombre": "CIRUGIA PLASTICA Y REPARADORA DE MANO"}, "model": "main.especialidad", "pk": "10112"}, {"fields": {"nombre": "ONCOLOGIA RADIOTERAPICA"}, "model": "main.especialidad", "pk": "10114"}, {"fields": {"nombre": "ALERGOLOGIA"}, "model": "main.especialidad", "pk": "10119"}, {"fields": {"nombre": "MEDICINA INTENSIVA Y DE EMERGENCIA"}, "model": "main.especialidad", "pk": "10130"}, {"fields": {"nombre": "DIPLOMATURA EN AUDITORIA MEDICA"}, "model": "main.especialidad", "pk": "A0001"}, {"fields": {"nombre": "DOCTORADO EN MEDICINA"}, "model": "main.especialidad", "pk": "D0001"}, {"fields": {"nombre": "DOCTORADO FILOSOFIA MENCION MEDICINA"}, "model": "main.especialidad", "pk": "D0002"}, {"fields": {"nombre": "DOCTORADO EN BIOQUIMICA Y NUTRICION"}, "model": "main.especialidad", "pk": "D0003"}, {"fields": {"nombre": "DOCTORADO EN CIRUGIA GENERAL"}, "model": "main.especialidad", "pk": "D0004"}, {"fields": {"nombre": "DOCTORADO EN CIENCIAS: SALUD PUBLICA"}, "model": "main.especialidad", "pk": "D0005"}, {"fields": {"nombre": "DOCTORADO EN SALUD PUBLICA"}, "model": "main.especialidad", "pk": "D0006"}, {"fields": {"nombre": "DOCTORADO EN SALUD PUBLICA AREA DE CONCENTRACION: SALUD MATERNO INFANTIL"}, "model": "main.especialidad", "pk": "D0007"}, {"fields": {"nombre": "DOCTORADO EN CIENCIAS DE LA SALUD"}, "model": "main.especialidad", "pk": "D0008"}, {"fields": {"nombre": "DOCTORADO EN MEDICINA Y CIRUGIA"}, "model": "main.especialidad", "pk": "D0009"}, {"fields": {"nombre": "DOCTORADO EN GESTION EN SALUD"}, "model": "main.especialidad", "pk": "D0010"}, {"fields": {"nombre": "DOCTORADO EN CIENCIAS"}, "model": "main.especialidad", "pk": "D0011"}, {"fields": {"nombre": "MAESTRIA EN MEDICINA"}, "model": "main.especialidad", "pk": "M0001"}, {"fields": {"nombre": "MAESTRIA EN ENFERMEDADES INFECCIOSAS "}, "model": "main.especialidad", "pk": "M0002"}, {"fields": {"nombre": "MAESTRIA CON MENCION EN NEUMOLOGIA"}, "model": "main.especialidad", "pk": "M0003"}, {"fields": {"nombre": "MAESTRIA EN OBSTETRICIA CON MENCION EN SALUD REPRODUCTIVA"}, "model": "main.especialidad", "pk": "M0004"}, {"fields": {"nombre": "MAESTRIA EN GESTION ESTRATEGICA DE LA CALIDAD Y AUDITORIA MEDICA"}, "model": "main.especialidad", "pk": "M0005"}, {"fields": {"nombre": "MAGISTER EN GOBIERNO Y GERENCIA EN SALUD"}, "model": "main.especialidad", "pk": "M0006"}, {"fields": {"nombre": "MAESTRIA EN EPIDEMIOLOGIA"}, "model": "main.especialidad", "pk": "M0007"}, {"fields": {"nombre": "MAESTRIA EN OFTALMOLOGIA"}, "model": "main.especialidad", "pk": "M0008"}, {"fields": {"nombre": "MAESTRIA EN CIENCIAS: ADMINISTRACION "}, "model": "main.especialidad", "pk": "M0009"}, {"fields": {"nombre": "MAESTRIA EN SALUD OCUPACIONAL"}, "model": "main.especialidad", "pk": "M0010"}, {"fields": {"nombre": "MAESTRIA EN SALUD PUBLICA"}, "model": "main.especialidad", "pk": "M0011"}, {"fields": {"nombre": "MAESTRIA EN GERENCIA DE SERVICIOS DE SALUD"}, "model": "main.especialidad", "pk": "M0012"}, {"fields": {"nombre": "MAESTRIA EN BIOMEDICAS BASICAS MENCION EN FISIOLOGIA"}, "model": "main.especialidad", "pk": "M0013"}, {"fields": {"nombre": "MAGISTER EN ECONOMIA Y GESTION DE LA SALUD"}, "model": "main.especialidad", "pk": "M0014"}, {"fields": {"nombre": "MAGISTER EN SALUD MENTAL DEL NI\u00d1O Y  ADOLESCENTE"}, "model": "main.especialidad", "pk": "M0015"}, {"fields": {"nombre": "MAESTRIA EN MEDICINA CON MENCION EN GINECOLOGIA Y OBSTETRICIA"}, "model": "main.especialidad", "pk": "M0016"}, {"fields": {"nombre": "MAESTRIA EN MEDICINA CON MENCION EN PEDIATRIA"}, "model": "main.especialidad", "pk": "M0017"}, {"fields": {"nombre": "MAESTRIA EN MEDICINA CON MENCION EN CIRUGIA GENERAL"}, "model": "main.especialidad", "pk": "M0018"}, {"fields": {"nombre": "MAESTRIA EN SALUD PUBLICA CON MENCION EN EPIDEMIOLOGIA"}, "model": "main.especialidad", "pk": "M0019"}, {"fields": {"nombre": "MAESTRIA EN ADMINISTRACION DE SERVICIOS DE SALUD"}, "model": "main.especialidad", "pk": "M0020"}, {"fields": {"nombre": "MAESTRIA EN MEDICINA CON MENCION EN GERENCIA EN SALUD"}, "model": "main.especialidad", "pk": "M0021"}, {"fields": {"nombre": "MAESTRIA EN SALUD PUBLICA CON MENCION PLANIFICACION Y GESTION"}, "model": "main.especialidad", "pk": "M0022"}, {"fields": {"nombre": "MAGISTER EN GERIATRIA Y GERONTOLOGIA"}, "model": "main.especialidad", "pk": "M0023"}, {"fields": {"nombre": "MAGISTER EN SALUD PUBLICA CON MENCION EN GESTION DE SERVICIOS DE SALUD"}, "model": "main.especialidad", "pk": "M0024"}, {"fields": {"nombre": "MAGISTER EN GERENCIA DE SERVICIOS DE SALUD CON MENCION EN SERVICIOS PUBLICOS DE SALUD"}, "model": "main.especialidad", "pk": "M0025"}, {"fields": {"nombre": "MAESTRIA EN GESTION Y CONDUCCION EN SALUD"}, "model": "main.especialidad", "pk": "M0026"}, {"fields": {"nombre": "MAESTRIA EN SALUD PUBLICA MENCION PLANIFICACION Y GESTION "}, "model": "main.especialidad", "pk": "M0027"}, {"fields": {"nombre": "MAGISTER EN DOCENCIA E INVESTIGACION EN SALUD"}, "model": "main.especialidad", "pk": "M0028"}, {"fields": {"nombre": "MAESTRIA EN CIENCIAS: SALUD PUBLICA CON MENCION EN AUDITORIA MEDICA"}, "model": "main.especialidad", "pk": "M0029"}, {"fields": {"nombre": "MAESTRIA EN SALUD PUBLICA CON MENCION EN GERENCIA"}, "model": "main.especialidad", "pk": "M0030"}, {"fields": {"nombre": "MAESTRIA EN CIENCIAS: SALUD PUBLICA CON MENCION DE GERENCIA DE SERVICIOS PUBLICOS"}, "model": "main.especialidad", "pk": "M0031"}, {"fields": {"nombre": "MAESTRIA EN SALUD PUBLIPA CON MENCION EN GESTION HOSPITALARIA"}, "model": "main.especialidad", "pk": "M0032"}, {"fields": {"nombre": "MAGISTER EN CIENCIAS EN PLANIFICACION Y FINANZAS EN SALUD"}, "model": "main.especialidad", "pk": "M0033"}, {"fields": {"nombre": "MAESTRIA EN EFERMEDADES INFECCIOSAS"}, "model": "main.especialidad", "pk": "M0034"}, {"fields": {"nombre": "MAESTRIA EN MEDICINA CON MENCION EN CIRUGIA PEDIATRICA"}, "model": "main.especialidad", "pk": "M0035"}, {"fields": {"nombre": "MAESTRIA EN CIENCIAS CON MENCION EN GERENCIA DE SERVICIOS DE SALUD"}, "model": "main.especialidad", "pk": "M0036"}, {"fields": {"nombre": "MAESTRIA EN FISIOLOGIA"}, "model": "main.especialidad", "pk": "M0037"}, {"fields": {"nombre": "MAESTRIA EN MEDICINA CON MENCION EN GASTROENTEROLOGIA"}, "model": "main.especialidad", "pk": "M0038"}, {"fields": {"nombre": "MAESTRIA EN MEDICINA CON MENCION EN CIRUGIA GENERAL Y ONCOLOGICA"}, "model": "main.especialidad", "pk": "M0039"}, {"fields": {"nombre": "MAESTRIA EN BIOQUIMICA Y NUTRICION"}, "model": "main.especialidad", "pk": "M0040"}, {"fields": {"nombre": "MAESTRIA EN CIENCIAS DE LA SALUD CON MENCION EN GESTION EN SERVICIOS DE SALUD"}, "model": "main.especialidad", "pk": "M0041"}, {"fields": {"nombre": "MAESTRIA EN CIENCIAS: ADMINISTRACION Y GESTION EN SALUD"}, "model": "main.especialidad", "pk": "M0042"}, {"fields": {"nombre": "MAESTRIA EN MEDICINA FAMILIAR, COMUNITARIA Y ATENCION PRIMARIA"}, "model": "main.especialidad", "pk": "M0043"}, {"fields": {"nombre": "MAESTRIA EN SALUD PUBLICA CON MENCION EN ADMINISTRACION HOSPITALARIA Y DE SERVICIO DE SALUD"}, "model": "main.especialidad", "pk": "M0044"}, {"fields": {"nombre": "MAESTRIA EN ADMINISTRACION DE EMPRESAS DE SALUD"}, "model": "main.especialidad", "pk": "M0045"}, {"fields": {"nombre": "MAESTRIA EN MICROBIOLOGIA"}, "model": "main.especialidad", "pk": "M0046"}, {"fields": {"nombre": "MAESTRIA EN CIENCIAS BASICAS MEDICAS CON MENCION EN FISIOLOGIA"}, "model": "main.especialidad", "pk": "M0047"}, {"fields": {"nombre": "MAESTRIA EN MEDICINA CON MENCION EN MEDICINA INTERNA"}, "model": "main.especialidad", "pk": "M0048"}, {"fields": {"nombre": "MAESTRIA EN ATENCION INTEGRAL AL NI\u00d1O"}, "model": "main.especialidad", "pk": "M0049"}, {"fields": {"nombre": "MAESTRIA EN GESTION Y CONDUCCION EN SALUD"}, "model": "main.especialidad", "pk": "M0050"}, {"fields": {"nombre": "MAESTRIA EN MEDICINA CON MENCION EN RADIOLOGIA"}, "model": "main.especialidad", "pk": "M0051"}, {"fields": {"nombre": "MAESTRIA EN SALUD PUBLICA CON MENCION EN SALUD FAMILIAR Y COMUNITARIA"}, "model": "main.especialidad", "pk": "M0052"}, {"fields": {"nombre": "MAESTRIA EN SALUD PUBLICA CON MENCION EN ADMINISTRACION Y GERENCIA EN LOS SERVICIOS DE SALUD"}, "model": "main.especialidad", "pk": "M0053"}, {"fields": {"nombre": "MAESTRIA EN URGENCIAS EN ATENCION PRIMARIA"}, "model": "main.especialidad", "pk": "M0054"}, {"fields": {"nombre": "MAESTRIA EN NEUROCIENCIAS"}, "model": "main.especialidad", "pk": "M0055"}, {"fields": {"nombre": "MAESTRIA EN PREVENCION DE RIESGOS Y SALUD OCUPACIONAL"}, "model": "main.especialidad", "pk": "M0056"}, {"fields": {"nombre": "MAESTRIA EN POLITICAS Y PLANIFICACION EN SALUD"}, "model": "main.especialidad", "pk": "M0057"}, {"fields": {"nombre": "MAESTRIA EN URGENCIAS MEDICAS EN ATENCION PRIMARIA"}, "model": "main.especialidad", "pk": "M0058"}, {"fields": {"nombre": "MAESTRIA EN CIENCIAS: SALUD PUBLICA CON MENCION EN GERENCIA DE SERVICIOS DE SALUD"}, "model": "main.especialidad", "pk": "M0059"}, {"fields": {"nombre": "MAESTRIA EN PREVENCION DE RIESGOS Y SALUD OCUPACIONAL, I EDICION"}, "model": "main.especialidad", "pk": "M0060"}, {"fields": {"nombre": "MAESTRIA EN SALUD LABORAL"}, "model": "main.especialidad", "pk": "M0061"}, {"fields": {"nombre": "MAESTRIA EN MEDICINA CON MENCION EN CIENCIAS CLINICAS"}, "model": "main.especialidad", "pk": "M0062"}, {"fields": {"nombre": "MAESTRIA EN DIRECCION Y GESTION DE SERVICIOS DE SALUD"}, "model": "main.especialidad", "pk": "M0063"}, {"fields": {"nombre": "MAESTRIA EN GESTION DE LOS SERVICIOS DE SALUD"}, "model": "main.especialidad", "pk": "M0064"}, {"fields": {"nombre": "MAESTRIA EN POLITICAS Y GESTION EN SALUD"}, "model": "main.especialidad", "pk": "M0065"}, {"fields": {"nombre": "MAESTRIA EN REHABILITACION EN SALUD"}, "model": "main.especialidad", "pk": "M0066"}, {"fields": {"nombre": "MAESTRIA EN CIENCIAS DE LA SALUD CON MECION EN GESTION EN SERVICIOS DE SALUD"}, "model": "main.especialidad", "pk": "M0067"}, {"fields": {"nombre": "MAESTRIA EN SALUD OCUPACIONAL Y AMBIENTAL"}, "model": "main.especialidad", "pk": "M0068"}, {"fields": {"nombre": "MAESTRIA EN INICIACION A LA INVESTIGACION EN MEDICINA"}, "model": "main.especialidad", "pk": "M0069"}, {"fields": {"nombre": "MAESTRIA EN CIENCIAS BASICAS MEDICAS CON MENCION EN BIOQUIMICA"}, "model": "main.especialidad", "pk": "M0070"}, {"fields": {"nombre": "MAESTRIA EN NUTRICION CON MENCION EN ASPECTOS BIOLOGICOS DE LA NUTRICION"}, "model": "main.especialidad", "pk": "M0071"}, {"fields": {"nombre": "MAESTRIA EN CIENCIAS DE LA SALUD"}, "model": "main.especialidad", "pk": "M0072"}, {"fields": {"nombre": "MAESTRIA EN SALUD PUBLICA MENCION: GERENCIA EN SERVICIOS DE SALUD"}, "model": "main.especialidad", "pk": "M0073"}, {"fields": {"nombre": "MAESTRIA EN CIENCIAS EN EL PROGRAMA DE SEGURIDAD Y SALUD OCUPACIONAL INTERNACIONAL"}, "model": "main.especialidad", "pk": "M0074"}, {"fields": {"nombre": "MAESTRIA EN CIENCIAS: AREA DE CONCENTRACION, POLITICAS, PLANIFICACION, GESTION Y PRACTICAS EN SALUD"}, "model": "main.especialidad", "pk": "M0075"}, {"fields": {"nombre": "MAESTRIA EN FARMACOLOGIA, DESAROLLO, EVALUACION Y UTILIZACION RACIONAL DE MEDICAMENTOS"}, "model": "main.especialidad", "pk": "M0076"}, {"fields": {"nombre": "MAESTRIA EN CIENCIA CON MENCION UNIVERSITARIA INVESTIGACION EDUCATIVA"}, "model": "main.especialidad", "pk": "MN001"}, {"fields": {"nombre": "MAESTRIA EN ADMINISTRACION"}, "model": "main.especialidad", "pk": "MN002"}]
